uipath_connectors/openai_openai/__init__.py
uipath_connectors/openai_openai/client.py
uipath_connectors/openai_openai/errors.py
uipath_connectors/openai_openai/py.typed
uipath_connectors/openai_openai/types.py
uipath_connectors/openai_openai/api/__init__.py
uipath_connectors/openai_openai/api/generate_text_completion/__init__.py
uipath_connectors/openai_openai/api/generate_text_completion/generate_text_completion.py
uipath_connectors/openai_openai/api/v2chatcompletion/__init__.py
uipath_connectors/openai_openai/api/v2chatcompletion/generate_chat_completion_v2.py
uipath_connectors/openai_openai/models/__init__.py
uipath_connectors/openai_openai/models/default_error.py
uipath_connectors/openai_openai/models/generate_chat_completion_v2_body.py
uipath_connectors/openai_openai/models/generate_chat_completion_v2_request.py
uipath_connectors/openai_openai/models/generate_chat_completion_v2_request_image_type.py
uipath_connectors/openai_openai/models/generate_chat_completion_v2_request_model.py
uipath_connectors/openai_openai/models/generate_chat_completion_v2_response.py
uipath_connectors/openai_openai/models/generate_chat_completion_v2_response_choices_array_item_ref.py
uipath_connectors/openai_openai/models/generate_chat_completion_v2_response_choices_message.py
uipath_connectors/openai_openai/models/generate_chat_completion_v2_response_model.py
uipath_connectors/openai_openai/models/generate_chat_completion_v2_response_usage.py
uipath_connectors/openai_openai/models/generate_text_completion_request.py
uipath_connectors/openai_openai/models/generate_text_completion_request_model.py
uipath_connectors/openai_openai/models/generate_text_completion_response.py
uipath_connectors/openai_openai/models/generate_text_completion_response_choices_array_item_ref.py
uipath_connectors/openai_openai/models/generate_text_completion_response_model.py
uipath_connectors/openai_openai/models/generate_text_completion_response_usage.py
uipath_connectors_openai_openai-1.15.9.dev12.dist-info/METADATA
uipath_connectors_openai_openai-1.15.9.dev12.dist-info/WHEEL
uipath_connectors_openai_openai-1.15.9.dev12.dist-info/entry_points.txt
uipath_connectors_openai_openai-1.15.9.dev12.dist-info/top_level.txt
uipath_connectors_openai_openai-1.15.9.dev12.dist-info/RECORD
